{
  "url": "https://www.hymnal.net/en/hymn/h/8067",
  "title": "Such a name as sweet as Jesus",
  "verses": [
    {
      "lines": [
        {
          "segments": [
            {
              "chord": "D",
              "text": "Such a"
            },
            {
              "chord": "",
              "text": "name as"
            },
            {
              "chord": "A",
              "text": "sweet as"
            },
            {
              "chord": "A7",
              "text": "\"Jesus\""
            }
          ]
        },
        {
          "segments": [
            {
              "chord": "D",
              "text": "Heav'n and"
            },
            {
              "chord": "G",
              "text": "earth do"
            },
            {
              "chord": "D",
              "text": "not"
            },
            {
              "chord": "A7",
              "text": "con"
            },
            {
              "chord": "D",
              "text": "tain;"
            }
          ]
        },
        {
          "segments": [
            {
              "chord": "",
              "text": "When our Savior"
            },
            {
              "chord": "A",
              "text": "left His"
            },
            {
              "chord": "A7",
              "text": "glory,"
            }
          ]
        },
        {
          "segments": [
            {
              "chord": "D",
              "text": "God gave"
            },
            {
              "chord": "G",
              "text": "Him this"
            },
            {
              "chord": "D",
              "text": "match"
            },
            {
              "chord": "A7",
              "text": "less"
            },
            {
              "chord": "D",
              "text": "name."
            }
          ]
        }
      ],
      "type": "verse",
      "number": "1"
    },
    {
      "lines": [
        {
          "segments": [
            {
              "chord": "",
              "text": "How we love to call, \"Lord"
            },
            {
              "chord": "A7",
              "text": "Jesus!\""
            }
          ]
        },
        {
          "segments": [
            {
              "chord": "D",
              "text": "To acknowledge"
            },
            {
              "chord": "Bm",
              "text": "Christ, God's"
            },
            {
              "chord": "A",
              "text": "Son."
            }
          ]
        },
        {
          "segments": [
            {
              "chord": "D",
              "text": "Never"
            },
            {
              "chord": "",
              "text": "was a"
            },
            {
              "chord": "A",
              "text": "name so"
            },
            {
              "chord": "A7",
              "text": "wond'rous,"
            }
          ]
        },
        {
          "segments": [
            {
              "chord": "D",
              "text": "Dear and"
            },
            {
              "chord": "G",
              "text": "sweet as"
            },
            {
              "chord": "A7",
              "text": "\"Je"
            },
            {
              "chord": "D",
              "text": "sus.\""
            }
          ]
        }
      ],
      "type": "chorus"
    },
    {
      "lines": [
        {
          "segments": [
            {
              "chord": "",
              "text": "When upon the tree they hung Him,"
            }
          ]
        },
        {
          "segments": [
            {
              "chord": "",
              "text": "There they also hung this name,"
            }
          ]
        },
        {
          "segments": [
            {
              "chord": "",
              "text": "For the whole earth’s admiration;"
            }
          ]
        },
        {
          "segments": [
            {
              "chord": "",
              "text": "See how truly we love Him!"
            }
          ]
        }
      ],
      "type": "verse",
      "number": "2"
    },
    {
      "lines": [
        {
          "segments": [
            {
              "chord": "",
              "text": "How we love to call, “Lord Jesus!”"
            }
          ]
        },
        {
          "segments": [
            {
              "chord": "",
              "text": "To acknowledge Christ, God’s Son."
            }
          ]
        },
        {
          "segments": [
            {
              "chord": "",
              "text": "Never was a name so wond’rous,"
            }
          ]
        },
        {
          "segments": [
            {
              "chord": "",
              "text": "Dear and sweet as “Jesus.”"
            }
          ]
        }
      ],
      "type": "chorus"
    },
    {
      "lines": [
        {
          "segments": [
            {
              "chord": "",
              "text": "Then enthroned in His ascension,"
            }
          ]
        },
        {
          "segments": [
            {
              "chord": "",
              "text": "God on Him this name conferred;"
            }
          ]
        },
        {
          "segments": [
            {
              "chord": "",
              "text": "All knees bowed, all tongues confessing,"
            }
          ]
        },
        {
          "segments": [
            {
              "chord": "",
              "text": "Hail Him, all in heav’n and earth!"
            }
          ]
        }
      ],
      "type": "verse",
      "number": "3"
    },
    {
      "lines": [
        {
          "segments": [
            {
              "chord": "",
              "text": "How we love to call, “Lord Jesus!”"
            }
          ]
        },
        {
          "segments": [
            {
              "chord": "",
              "text": "To acknowledge Christ, God’s Son."
            }
          ]
        },
        {
          "segments": [
            {
              "chord": "",
              "text": "Never was a name so wond’rous,"
            }
          ]
        },
        {
          "segments": [
            {
              "chord": "",
              "text": "Dear and sweet as “Jesus.”"
            }
          ]
        }
      ],
      "type": "chorus"
    },
    {
      "lines": [
        {
          "segments": [
            {
              "chord": "",
              "text": "Grace unending and exhaustless"
            }
          ]
        },
        {
          "segments": [
            {
              "chord": "",
              "text": "Issues from Thy matchless name;"
            }
          ]
        },
        {
          "segments": [
            {
              "chord": "",
              "text": "Yesterday, today, forever,"
            }
          ]
        },
        {
          "segments": [
            {
              "chord": "",
              "text": "Thou, our JESUS, art the same!"
            }
          ]
        }
      ],
      "type": "verse",
      "number": "4"
    },
    {
      "lines": [
        {
          "segments": [
            {
              "chord": "",
              "text": "How we love to call, “Lord Jesus!”"
            }
          ]
        },
        {
          "segments": [
            {
              "chord": "",
              "text": "To acknowledge Christ, God’s Son."
            }
          ]
        },
        {
          "segments": [
            {
              "chord": "",
              "text": "Never was a name so wond’rous,"
            }
          ]
        },
        {
          "segments": [
            {
              "chord": "",
              "text": "Dear and sweet as “Jesus.”"
            }
          ]
        }
      ],
      "type": "chorus"
    }
  ],
  "metadata": {
    "category": "Praise of the Lord",
    "time": "2/4",
    "hymn_code": "1231232123432",
    "midi_tune_url": "https://www.hymnal.net/Hymns/Hymnal/midi/tunes/e8067_tune.midi",
    "guitar_leadsheet_url": "https://www.hymnal.net/Hymns/Hymnal/svg/e8067_g.svg",
    "current_key": "F Major",
    "original_key": "D Major",
    "capo": 3,
    "related": [
      {
        "url": "https://www.hymnal.net/cn/hymn/ch/67",
        "language": "cn",
        "category": "ch",
        "number": "67",
        "title": "C67"
      }
    ]
  },
  "raw_sections": [
    "Such aname assweet as\"Jesus\"",
    "Heav'n andearth donotcontain;",
    "When our Saviorleft Hisglory,",
    "God gaveHim thismatchlessname.",
    "How we love to call, \"LordJesus!\"",
    "To acknowledgeChrist, God'sSon.",
    "Neverwas aname sowond'rous,",
    "Dear andsweet as\"Jesus.\"",
    "When upon the tree they hung Him,",
    "There they also hung this name,",
    "For the whole earth’s admiration;",
    "See how truly we love Him!",
    "How we love to call, “Lord Jesus!”",
    "To acknowledge Christ, God’s Son.",
    "Never was a name so wond’rous,",
    "Dear and sweet as “Jesus.”",
    "Then enthroned in His ascension,",
    "God on Him this name conferred;",
    "All knees bowed, all tongues confessing,",
    "Hail Him, all in heav’n and earth!",
    "How we love to call, “Lord Jesus!”",
    "To acknowledge Christ, God’s Son.",
    "Never was a name so wond’rous,",
    "Dear and sweet as “Jesus.”",
    "Grace unending and exhaustless",
    "Issues from Thy matchless name;",
    "Yesterday, today, forever,",
    "Thou, our JESUS, art the same!",
    "How we love to call, “Lord Jesus!”",
    "To acknowledge Christ, God’s Son.",
    "Never was a name so wond’rous,",
    "Dear and sweet as “Jesus.”"
  ]
}